crypto_exchange/__init__.py
crypto_exchange/config.py
crypto_exchange/exchanges.py
crypto_exchange/manager.py
tests/__init__.py
tests/test_exchanges.py
crypto_exchange_api-0.1.8.dist-info/METADATA
crypto_exchange_api-0.1.8.dist-info/WHEEL
crypto_exchange_api-0.1.8.dist-info/top_level.txt
crypto_exchange_api-0.1.8.dist-info/RECORD
