Metadata-Version: 2.1
Name: crypto_exchange_api
Version: 0.1.8
Summary: A Python framework for accessing multiple cryptocurrency exchanges APIs
Home-page: https://github.com/hedeqiang/python_crypto_exchange_api
Author: hedeqiang
Author-email: laravel_code@163.com
License: MIT
Classifier: Programming Language :: Python :: 3
Classifier: License :: OSI Approved :: MIT License
Classifier: Operating System :: OS Independent
Requires-Python: >=3.6
Requires-Dist: requests
